{"status":0,"data":[{"id":100001,"parentId":0,"name":"one","status":true,"sortOrder":null,"createTime":1490431560000,"updateTime":1490431560000},{"id":100002,"parentId":0,"name":"8","status":true,"sortOrder":null,"createTime":1490431581000,"updateTime":1490431581000},{"id":100003,"parentId":0,"name":"nullooooooooo","status":true,"sortOrder":null,"createTime":1490431793000,"updateTime":1490431793000},{"id":100004,"parentId":0,"name":"9856230.","status":true,"sortOrder":null,"createTime":1490431819000,"updateTime":1490431819000},{"id":100005,"parentId":0,"name":"1155555","status":true,"sortOrder":null,"createTime":1490431829000,"updateTime":1490431829000},{"id":100035,"parentId":0,"name":"666","status":true,"sortOrder":null,"createTime":1578148824000,"updateTime":1578148824000},{"id":100037,"parentId":0,"name":"大威天龙5656565","status":true,"sortOrder":null,"createTime":1578212568000,"updateTime":1578212568000},{"id":100042,"parentId":0,"name":"大威天龙100004","status":true,"sortOrder":null,"createTime":1578461609000,"updateTime":1578461609000},{"id":100044,"parentId":0,"name":"大威天龙100044","status":true,"sortOrder":null,"createTime":1578898961000,"updateTime":1578898961000},{"id":100054,"parentId":0,"name":"大威天龙100054","status":true,"sortOrder":null,"createTime":1579283139000,"updateTime":1579283139000},{"id":100056,"parentId":0,"name":"大威天龙100056","status":true,"sortOrder":null,"createTime":1579285853000,"updateTime":1579285853000},{"id":100057,"parentId":0,"name":"大威天龙100057","status":true,"sortOrder":null,"createTime":1579285894000,"updateTime":1579285894000},{"id":100058,"parentId":0,"name":"大威天龙100058","status":true,"sortOrder":null,"createTime":1579286003000,"updateTime":1579286003000},{"id":100059,"parentId":0,"name":"大威天龙100059","status":true,"sortOrder":null,"createTime":1579286100000,"updateTime":1579286100000},{"id":100061,"parentId":0,"name":"大威天龙100061","status":true,"sortOrder":null,"createTime":1579287270000,"updateTime":1579287270000},{"id":100062,"parentId":0,"name":"大威天龙100062","status":true,"sortOrder":null,"createTime":1579620472000,"updateTime":1579620472000},{"id":100064,"parentId":0,"name":"大威天龙100064","status":true,"sortOrder":null,"createTime":1579754173000,"updateTime":1579754173000},{"id":100066,"parentId":0,"name":"大威天龙100066","status":true,"sortOrder":null,"createTime":1580462594000,"updateTime":1580462594000},{"id":100067,"parentId":0,"name":"大威天龙100067","status":true,"sortOrder":null,"createTime":1580528104000,"updateTime":1580528104000},{"id":100068,"parentId":0,"name":"大威天龙100068","status":true,"sortOrder":null,"createTime":1580528864000,"updateTime":1580528864000},{"id":100069,"parentId":0,"name":"大威天龙100069","status":true,"sortOrder":null,"createTime":1580529603000,"updateTime":1580529603000},{"id":100070,"parentId":0,"name":"大威天龙100070","status":true,"sortOrder":null,"createTime":1580529716000,"updateTime":1580529716000},{"id":100077,"parentId":0,"name":"大威天龙100077","status":true,"sortOrder":null,"createTime":1581235843000,"updateTime":1581235843000},{"id":100079,"parentId":0,"name":"大威天龙100079","status":true,"sortOrder":null,"createTime":1581408474000,"updateTime":1581408474000},{"id":100083,"parentId":0,"name":"大威天龙100083","status":true,"sortOrder":null,"createTime":1581749049000,"updateTime":1581749049000},{"id":100084,"parentId":0,"name":"大威天龙100084","status":true,"sortOrder":null,"createTime":1581749071000,"updateTime":1581749071000},{"id":100085,"parentId":0,"name":"大威天龙100085","status":true,"sortOrder":null,"createTime":1581749073000,"updateTime":1581749073000},{"id":100086,"parentId":0,"name":"大威天龙100086","status":true,"sortOrder":null,"createTime":1581749105000,"updateTime":1581749105000},{"id":100087,"parentId":0,"name":"大威天龙100087","status":true,"sortOrder":null,"createTime":1581749185000,"updateTime":1581749185000},{"id":100088,"parentId":0,"name":"大威天龙100088","status":true,"sortOrder":null,"createTime":1581749203000,"updateTime":1581749203000},{"id":100089,"parentId":0,"name":"大威天龙100089","status":true,"sortOrder":null,"createTime":1581749417000,"updateTime":1581749417000},{"id":100095,"parentId":0,"name":"大威天龙100095","status":true,"sortOrder":null,"createTime":1581749804000,"updateTime":1581749804000},{"id":100096,"parentId":0,"name":"大威天龙100096","status":true,"sortOrder":null,"createTime":1581749830000,"updateTime":1581749830000},{"id":100097,"parentId":0,"name":"大威天龙100097","status":true,"sortOrder":null,"createTime":1581749846000,"updateTime":1581749846000},{"id":100100,"parentId":0,"name":"大威天龙100100","status":true,"sortOrder":null,"createTime":1581908100000,"updateTime":1581908100000},{"id":100101,"parentId":0,"name":"大威天龙100101","status":true,"sortOrder":null,"createTime":1581908120000,"updateTime":1581908120000},{"id":100105,"parentId":0,"name":"大威天龙100105","status":true,"sortOrder":null,"createTime":1582022343000,"updateTime":1582022343000},{"id":100107,"parentId":0,"name":"大威天龙100107","status":true,"sortOrder":null,"createTime":1582130124000,"updateTime":1582130124000},{"id":100108,"parentId":0,"name":"大威天龙100108","status":true,"sortOrder":null,"createTime":1582175207000,"updateTime":1582175207000},{"id":100112,"parentId":0,"name":"大威天龙100112","status":true,"sortOrder":null,"createTime":1582204073000,"updateTime":1582204073000},{"id":100114,"parentId":0,"name":"大威天龙100114","status":true,"sortOrder":null,"createTime":1582204279000,"updateTime":1582204279000},{"id":100117,"parentId":0,"name":"大威天龙100117","status":true,"sortOrder":null,"createTime":1582384884000,"updateTime":1582384884000},{"id":100122,"parentId":0,"name":"大威天龙100122","status":true,"sortOrder":null,"createTime":1582459283000,"updateTime":1582459283000},{"id":100123,"parentId":0,"name":"大威天龙100123","status":true,"sortOrder":null,"createTime":1582459446000,"updateTime":1582459446000},{"id":100127,"parentId":0,"name":"大威天龙100127","status":true,"sortOrder":null,"createTime":1582790419000,"updateTime":1582790419000},{"id":100129,"parentId":0,"name":"大威天龙100129","status":true,"sortOrder":null,"createTime":1582877194000,"updateTime":1582877194000},{"id":100131,"parentId":0,"name":"大威天龙100131","status":true,"sortOrder":null,"createTime":1582950329000,"updateTime":1582950329000},{"id":100132,"parentId":0,"name":"大威天龙100132","status":true,"sortOrder":null,"createTime":1582950391000,"updateTime":1582950391000},{"id":100133,"parentId":0,"name":"大威天龙100133","status":true,"sortOrder":null,"createTime":1582950473000,"updateTime":1582950473000},{"id":100134,"parentId":0,"name":"大威天龙100134","status":true,"sortOrder":null,"createTime":1582950532000,"updateTime":1582950532000},{"id":100135,"parentId":0,"name":"大威天龙100135","status":true,"sortOrder":null,"createTime":1582950558000,"updateTime":1582950558000},{"id":100138,"parentId":0,"name":"大威天龙100138","status":true,"sortOrder":null,"createTime":1582995091000,"updateTime":1582995091000},{"id":100139,"parentId":0,"name":"大威天龙100139","status":true,"sortOrder":null,"createTime":1582995144000,"updateTime":1582995144000},{"id":100142,"parentId":0,"name":"大威天龙100142","status":true,"sortOrder":null,"createTime":1583065120000,"updateTime":1583065120000},{"id":100149,"parentId":0,"name":"大威天龙100149","status":true,"sortOrder":null,"createTime":1583134398000,"updateTime":1583134398000},{"id":100150,"parentId":0,"name":"大威天龙100150","status":true,"sortOrder":null,"createTime":1583134433000,"updateTime":1583134433000},{"id":100151,"parentId":0,"name":"大威天龙100151","status":true,"sortOrder":null,"createTime":1583134452000,"updateTime":1583134452000},{"id":100152,"parentId":0,"name":"大威天龙100152","status":true,"sortOrder":null,"createTime":1583134464000,"updateTime":1583134464000},{"id":100153,"parentId":0,"name":"大威天龙100153","status":true,"sortOrder":null,"createTime":1583134479000,"updateTime":1583134479000},{"id":100156,"parentId":0,"name":"大威天龙100156","status":true,"sortOrder":null,"createTime":1583221020000,"updateTime":1583221020000},{"id":100165,"parentId":0,"name":"大威天龙100165","status":true,"sortOrder":null,"createTime":1583484958000,"updateTime":1583484958000},{"id":100168,"parentId":0,"name":"大威天龙100168","status":true,"sortOrder":null,"createTime":1583485391000,"updateTime":1583485391000},{"id":100169,"parentId":0,"name":"大威天龙100169","status":true,"sortOrder":null,"createTime":1583488081000,"updateTime":1583488081000},{"id":100171,"parentId":0,"name":"大威天龙100171","status":true,"sortOrder":null,"createTime":1583571674000,"updateTime":1583571674000},{"id":100176,"parentId":0,"name":"大威天龙100176","status":true,"sortOrder":null,"createTime":1583600348000,"updateTime":1583600348000},{"id":100177,"parentId":0,"name":"大威天龙100177","status":true,"sortOrder":null,"createTime":1583634122000,"updateTime":1583634122000},{"id":100178,"parentId":0,"name":"大威天龙100178","status":true,"sortOrder":null,"createTime":1583634510000,"updateTime":1583634510000},{"id":100179,"parentId":0,"name":"大威天龙100179","status":true,"sortOrder":null,"createTime":1583634517000,"updateTime":1583634517000},{"id":100180,"parentId":0,"name":"大威天龙100180","status":true,"sortOrder":null,"createTime":1583634565000,"updateTime":1583634565000},{"id":100183,"parentId":0,"name":"大威天龙100183","status":true,"sortOrder":null,"createTime":1583644355000,"updateTime":1583644355000},{"id":100190,"parentId":0,"name":"大威天龙100190","status":true,"sortOrder":null,"createTime":1583994470000,"updateTime":1583994470000},{"id":100193,"parentId":0,"name":"大威天龙100193","status":true,"sortOrder":null,"createTime":1584080341000,"updateTime":1584080341000},{"id":100199,"parentId":0,"name":"大威天龙100199","status":true,"sortOrder":null,"createTime":1584087649000,"updateTime":1584087649000},{"id":100200,"parentId":0,"name":"大威天龙100200","status":true,"sortOrder":null,"createTime":1584087728000,"updateTime":1584087728000},{"id":100201,"parentId":0,"name":"大威天龙100201","status":true,"sortOrder":null,"createTime":1584087797000,"updateTime":1584087797000},{"id":100202,"parentId":0,"name":"大威天龙100202","status":true,"sortOrder":null,"createTime":1584087834000,"updateTime":1584087834000},{"id":100203,"parentId":0,"name":"大威天龙100203","status":true,"sortOrder":null,"createTime":1584104675000,"updateTime":1584104675000},{"id":100204,"parentId":0,"name":"大威天龙100204","status":true,"sortOrder":null,"createTime":1584106092000,"updateTime":1584106092000},{"id":100205,"parentId":0,"name":"大威天龙100205","status":true,"sortOrder":null,"createTime":1584106222000,"updateTime":1584106222000},{"id":100220,"parentId":0,"name":"大威天龙100220","status":true,"sortOrder":null,"createTime":1584167542000,"updateTime":1584167542000},{"id":100221,"parentId":0,"name":"大威天龙100221","status":true,"sortOrder":null,"createTime":1584167709000,"updateTime":1584167709000},{"id":100222,"parentId":0,"name":"大威天龙100222","status":true,"sortOrder":null,"createTime":1584190000000,"updateTime":1584190000000},{"id":100224,"parentId":0,"name":"大威天龙100224","status":true,"sortOrder":null,"createTime":1584190188000,"updateTime":1584190188000},{"id":100225,"parentId":0,"name":"大威天龙100225","status":true,"sortOrder":null,"createTime":1584190221000,"updateTime":1584190221000},{"id":100227,"parentId":0,"name":"大威天龙100227","status":true,"sortOrder":null,"createTime":1584190289000,"updateTime":1584190289000},{"id":100229,"parentId":0,"name":"大威天龙100229","status":true,"sortOrder":null,"createTime":1584198627000,"updateTime":1584198627000},{"id":100231,"parentId":0,"name":"大威天龙100231","status":true,"sortOrder":null,"createTime":1584201121000,"updateTime":1584201121000},{"id":100232,"parentId":0,"name":"大威天龙100232","status":true,"sortOrder":null,"createTime":1584201226000,"updateTime":1584201226000},{"id":100233,"parentId":0,"name":"大威天龙100233","status":true,"sortOrder":null,"createTime":1584201310000,"updateTime":1584201310000},{"id":100234,"parentId":0,"name":"大威天龙100234","status":true,"sortOrder":null,"createTime":1584201357000,"updateTime":1584201357000},{"id":100239,"parentId":0,"name":"大威天龙100239","status":true,"sortOrder":null,"createTime":1584262579000,"updateTime":1584262579000},{"id":100240,"parentId":0,"name":"大威天龙100240","status":true,"sortOrder":null,"createTime":1584266105000,"updateTime":1584266105000},{"id":100241,"parentId":0,"name":"大威天龙100241","status":true,"sortOrder":null,"createTime":1584266121000,"updateTime":1584266121000},{"id":100242,"parentId":0,"name":"大威天龙100242","status":true,"sortOrder":null,"createTime":1584266293000,"updateTime":1584266293000},{"id":100243,"parentId":0,"name":"大威天龙100243","status":true,"sortOrder":null,"createTime":1584266327000,"updateTime":1584266327000},{"id":100244,"parentId":0,"name":"大威天龙100244","status":true,"sortOrder":null,"createTime":1584266363000,"updateTime":1584266363000},{"id":100246,"parentId":0,"name":"大威天龙100246","status":true,"sortOrder":null,"createTime":1584266510000,"updateTime":1584266510000},{"id":100247,"parentId":0,"name":"大威天龙100247","status":true,"sortOrder":null,"createTime":1584266542000,"updateTime":1584266542000},{"id":100248,"parentId":0,"name":"大威天龙100248","status":true,"sortOrder":null,"createTime":1584266563000,"updateTime":1584266563000},{"id":100249,"parentId":0,"name":"大威天龙100249","status":true,"sortOrder":null,"createTime":1584266575000,"updateTime":1584266575000},{"id":100250,"parentId":0,"name":"大威天龙100250","status":true,"sortOrder":null,"createTime":1584266794000,"updateTime":1584266794000},{"id":100251,"parentId":0,"name":"大威天龙100251","status":true,"sortOrder":null,"createTime":1584266833000,"updateTime":1584266833000},{"id":100252,"parentId":0,"name":"大威天龙100252","status":true,"sortOrder":null,"createTime":1584266865000,"updateTime":1584266865000},{"id":100253,"parentId":0,"name":"大威天龙100253","status":true,"sortOrder":null,"createTime":1584267188000,"updateTime":1584267188000},{"id":100254,"parentId":0,"name":"大威天龙100254","status":true,"sortOrder":null,"createTime":1584267298000,"updateTime":1584267298000},{"id":100255,"parentId":0,"name":"大威天龙100255","status":true,"sortOrder":null,"createTime":1584267334000,"updateTime":1584267334000},{"id":100256,"parentId":0,"name":"大威天龙100256","status":true,"sortOrder":null,"createTime":1584267346000,"updateTime":1584267346000},{"id":100258,"parentId":0,"name":"大威天龙100258","status":true,"sortOrder":null,"createTime":1584267510000,"updateTime":1584267510000},{"id":100259,"parentId":0,"name":"大威天龙100259","status":true,"sortOrder":null,"createTime":1584267547000,"updateTime":1584267547000},{"id":100260,"parentId":0,"name":"大威天龙100260","status":true,"sortOrder":null,"createTime":1584267583000,"updateTime":1584267583000},{"id":100261,"parentId":0,"name":"大威天龙100261","status":true,"sortOrder":null,"createTime":1584267584000,"updateTime":1584267584000},{"id":100262,"parentId":0,"name":"大威天龙100262","status":true,"sortOrder":null,"createTime":1584267585000,"updateTime":1584267585000},{"id":100263,"parentId":0,"name":"大威天龙100263","status":true,"sortOrder":null,"createTime":1584267585000,"updateTime":1584267585000},{"id":100271,"parentId":0,"name":"大威天龙100271","status":true,"sortOrder":null,"createTime":1584275939000,"updateTime":1584275939000},{"id":100276,"parentId":0,"name":"大威天龙100276","status":true,"sortOrder":null,"createTime":1584333226000,"updateTime":1584333226000},{"id":100277,"parentId":0,"name":"大威天龙100277","status":true,"sortOrder":null,"createTime":1584336469000,"updateTime":1584336469000},{"id":100278,"parentId":0,"name":"大威天龙100278","status":true,"sortOrder":null,"createTime":1584336550000,"updateTime":1584336550000},{"id":100282,"parentId":0,"name":"大威天龙100282","status":true,"sortOrder":null,"createTime":1584362920000,"updateTime":1584362920000},{"id":100287,"parentId":0,"name":"大威天龙100287","status":true,"sortOrder":null,"createTime":1584433300000,"updateTime":1584433300000},{"id":100289,"parentId":0,"name":"大威天龙100289","status":true,"sortOrder":null,"createTime":1584446613000,"updateTime":1584446613000},{"id":100290,"parentId":0,"name":"大威天龙100290","status":true,"sortOrder":null,"createTime":1584446638000,"updateTime":1584446638000},{"id":100292,"parentId":0,"name":"大威天龙100292","status":true,"sortOrder":null,"createTime":1584610513000,"updateTime":1584610513000},{"id":100293,"parentId":0,"name":"大威天龙100293","status":true,"sortOrder":null,"createTime":1584610533000,"updateTime":1584610533000},{"id":100296,"parentId":0,"name":"大威天龙100296","status":true,"sortOrder":null,"createTime":1584630762000,"updateTime":1584630762000},{"id":100300,"parentId":0,"name":"大威天龙100300","status":true,"sortOrder":null,"createTime":1584691289000,"updateTime":1584691289000},{"id":100303,"parentId":0,"name":"大威天龙100303","status":true,"sortOrder":null,"createTime":1584691854000,"updateTime":1584691854000},{"id":100314,"parentId":0,"name":"大威天龙100314","status":true,"sortOrder":null,"createTime":1584716385000,"updateTime":1584716385000},{"id":100315,"parentId":0,"name":"大威天龙100315","status":true,"sortOrder":null,"createTime":1584717028000,"updateTime":1584717028000},{"id":100316,"parentId":0,"name":"大威天龙100316","status":true,"sortOrder":null,"createTime":1584717071000,"updateTime":1584717071000},{"id":100317,"parentId":0,"name":"大威天龙100317","status":true,"sortOrder":null,"createTime":1584717108000,"updateTime":1584717108000},{"id":100318,"parentId":0,"name":"大威天龙100318","status":true,"sortOrder":null,"createTime":1584717323000,"updateTime":1584717323000},{"id":100319,"parentId":0,"name":"大威天龙100319","status":true,"sortOrder":null,"createTime":1584717414000,"updateTime":1584717414000},{"id":100320,"parentId":0,"name":"大威天龙100320","status":true,"sortOrder":null,"createTime":1584718016000,"updateTime":1584718016000},{"id":100321,"parentId":0,"name":"大威天龙100321","status":true,"sortOrder":null,"createTime":1584718347000,"updateTime":1584718347000},{"id":100322,"parentId":0,"name":"大威天龙100322","status":true,"sortOrder":null,"createTime":1584776059000,"updateTime":1584776059000},{"id":100323,"parentId":0,"name":"大威天龙100323","status":true,"sortOrder":null,"createTime":1584779746000,"updateTime":1584779746000},{"id":100324,"parentId":0,"name":"大威天龙100324","status":true,"sortOrder":null,"createTime":1584779763000,"updateTime":1584779763000},{"id":100328,"parentId":0,"name":"大威天龙100328","status":true,"sortOrder":null,"createTime":1584872553000,"updateTime":1584872553000},{"id":100329,"parentId":0,"name":"大威天龙100329","status":true,"sortOrder":null,"createTime":1584872615000,"updateTime":1584872615000},{"id":100330,"parentId":0,"name":"大威天龙100330","status":true,"sortOrder":null,"createTime":1584874178000,"updateTime":1584874178000},{"id":100337,"parentId":0,"name":"大威天龙100337","status":true,"sortOrder":null,"createTime":1584881780000,"updateTime":1584881780000},{"id":100338,"parentId":0,"name":"大威天龙100338","status":true,"sortOrder":null,"createTime":1584881812000,"updateTime":1584881812000},{"id":100339,"parentId":0,"name":"大威天龙100339","status":true,"sortOrder":null,"createTime":1584881827000,"updateTime":1584881827000},{"id":100344,"parentId":0,"name":"大威天龙100344","status":true,"sortOrder":null,"createTime":1584882298000,"updateTime":1584882298000},{"id":100345,"parentId":0,"name":"大威天龙100345","status":true,"sortOrder":null,"createTime":1584884572000,"updateTime":1584884572000},{"id":100351,"parentId":0,"name":"大威天龙100351","status":true,"sortOrder":null,"createTime":1584902093000,"updateTime":1584902093000},{"id":100360,"parentId":0,"name":"大威天龙100360","status":true,"sortOrder":null,"createTime":1584962474000,"updateTime":1584962474000},{"id":100361,"parentId":0,"name":"大威天龙100361","status":true,"sortOrder":null,"createTime":1584962488000,"updateTime":1584962488000},{"id":100362,"parentId":0,"name":"大威天龙100362","status":true,"sortOrder":null,"createTime":1584967280000,"updateTime":1584967280000},{"id":100363,"parentId":0,"name":"大威天龙100363","status":true,"sortOrder":null,"createTime":1584967922000,"updateTime":1584967922000},{"id":100364,"parentId":0,"name":"大威天龙100364","status":true,"sortOrder":null,"createTime":1584967946000,"updateTime":1584967946000},{"id":100365,"parentId":0,"name":"大威天龙100365","status":true,"sortOrder":null,"createTime":1584968782000,"updateTime":1584968782000},{"id":100366,"parentId":0,"name":"大威天龙100366","status":true,"sortOrder":null,"createTime":1584969184000,"updateTime":1584969184000},{"id":100367,"parentId":0,"name":"大威天龙100367","status":true,"sortOrder":null,"createTime":1585027982000,"updateTime":1585027982000},{"id":100369,"parentId":0,"name":"大威天龙100369","status":true,"sortOrder":null,"createTime":1585145096000,"updateTime":1585145096000},{"id":100374,"parentId":0,"name":"大威天龙100374","status":true,"sortOrder":null,"createTime":1585187571000,"updateTime":1585187571000},{"id":100375,"parentId":0,"name":"大威天龙100375","status":true,"sortOrder":null,"createTime":1585190022000,"updateTime":1585190022000},{"id":100376,"parentId":0,"name":"大威天龙100376","status":true,"sortOrder":null,"createTime":1585190654000,"updateTime":1585190654000},{"id":100378,"parentId":0,"name":"大威天龙100378","status":true,"sortOrder":null,"createTime":1585199167000,"updateTime":1585199167000},{"id":100380,"parentId":0,"name":"大威天龙100380","status":true,"sortOrder":null,"createTime":1585290362000,"updateTime":1585290362000},{"id":100381,"parentId":0,"name":"大威天龙100381","status":true,"sortOrder":null,"createTime":1585292735000,"updateTime":1585292735000},{"id":100384,"parentId":0,"name":"大威天龙100384","status":true,"sortOrder":null,"createTime":1585299970000,"updateTime":1585299970000},{"id":100387,"parentId":0,"name":"大威天龙100387","status":true,"sortOrder":null,"createTime":1585321050000,"updateTime":1585321050000},{"id":100388,"parentId":0,"name":"大威天龙100388","status":true,"sortOrder":null,"createTime":1585321069000,"updateTime":1585321069000},{"id":100389,"parentId":0,"name":"大威天龙100389","status":true,"sortOrder":null,"createTime":1585456696000,"updateTime":1585456696000},{"id":100390,"parentId":0,"name":"大威天龙100390","status":true,"sortOrder":null,"createTime":1585457827000,"updateTime":1585457827000},{"id":100391,"parentId":0,"name":"大威天龙100391","status":true,"sortOrder":null,"createTime":1585460168000,"updateTime":1585460168000},{"id":100392,"parentId":0,"name":"大威天龙100392","status":true,"sortOrder":null,"createTime":1585460416000,"updateTime":1585460416000},{"id":100393,"parentId":0,"name":"大威天龙100393","status":true,"sortOrder":null,"createTime":1585467154000,"updateTime":1585467154000},{"id":100394,"parentId":0,"name":"大威天龙100394","status":true,"sortOrder":null,"createTime":1585467419000,"updateTime":1585467419000},{"id":100395,"parentId":0,"name":"大威天龙100395","status":true,"sortOrder":null,"createTime":1585469182000,"updateTime":1585469182000},{"id":100396,"parentId":0,"name":"大威天龙100396","status":true,"sortOrder":null,"createTime":1585469202000,"updateTime":1585469202000},{"id":100397,"parentId":0,"name":"大威天龙100397","status":true,"sortOrder":null,"createTime":1585479518000,"updateTime":1585479518000},{"id":100398,"parentId":0,"name":"大威天龙100398","status":true,"sortOrder":null,"createTime":1585480183000,"updateTime":1585480183000},{"id":100399,"parentId":0,"name":"大威天龙100399","status":true,"sortOrder":null,"createTime":1585480563000,"updateTime":1585480563000},{"id":100400,"parentId":0,"name":"大威天龙100400","status":true,"sortOrder":null,"createTime":1585481005000,"updateTime":1585481005000},{"id":100403,"parentId":0,"name":"大威天龙100403","status":true,"sortOrder":null,"createTime":1585488470000,"updateTime":1585488470000},{"id":100404,"parentId":0,"name":"大威天龙100404","status":true,"sortOrder":null,"createTime":1585491042000,"updateTime":1585491042000},{"id":100405,"parentId":0,"name":"大威天龙100405","status":true,"sortOrder":null,"createTime":1585491044000,"updateTime":1585491044000},{"id":100410,"parentId":0,"name":"大威天龙100410","status":true,"sortOrder":null,"createTime":1585494286000,"updateTime":1585494286000},{"id":100411,"parentId":0,"name":"大威天龙100411","status":true,"sortOrder":null,"createTime":1585495083000,"updateTime":1585495083000},{"id":100415,"parentId":0,"name":"大威天龙100415","status":true,"sortOrder":null,"createTime":1585550134000,"updateTime":1585550134000},{"id":100416,"parentId":0,"name":"大威天龙100416","status":true,"sortOrder":null,"createTime":1585550284000,"updateTime":1585550284000},{"id":100419,"parentId":0,"name":"大威天龙100419","status":true,"sortOrder":null,"createTime":1585553249000,"updateTime":1585553249000},{"id":100421,"parentId":0,"name":"大威天龙100421","status":true,"sortOrder":null,"createTime":1585555416000,"updateTime":1585555416000},{"id":100422,"parentId":0,"name":"大威天龙100422","status":true,"sortOrder":null,"createTime":1585555469000,"updateTime":1585555469000},{"id":100423,"parentId":0,"name":"大威天龙100423","status":true,"sortOrder":null,"createTime":1585555516000,"updateTime":1585555516000},{"id":100424,"parentId":0,"name":"大威天龙100424","status":true,"sortOrder":null,"createTime":1585555716000,"updateTime":1585555716000},{"id":100425,"parentId":0,"name":"大威天龙100425","status":true,"sortOrder":null,"createTime":1585564446000,"updateTime":1585564446000},{"id":100427,"parentId":0,"name":"大威天龙100427","status":true,"sortOrder":null,"createTime":1585570419000,"updateTime":1585570419000},{"id":100434,"parentId":0,"name":"大威天龙100434","status":true,"sortOrder":null,"createTime":1585721267000,"updateTime":1585721267000},{"id":100436,"parentId":0,"name":"大威天龙100436","status":true,"sortOrder":null,"createTime":1585724418000,"updateTime":1585724418000},{"id":100437,"parentId":0,"name":"大威天龙100437","status":true,"sortOrder":null,"createTime":1585724470000,"updateTime":1585724470000},{"id":100438,"parentId":0,"name":"大威天龙100438","status":true,"sortOrder":null,"createTime":1585725576000,"updateTime":1585725576000},{"id":100439,"parentId":0,"name":"大威天龙100439","status":true,"sortOrder":null,"createTime":1585725816000,"updateTime":1585725816000},{"id":100440,"parentId":0,"name":"大威天龙100440","status":true,"sortOrder":null,"createTime":1585726198000,"updateTime":1585726198000},{"id":100441,"parentId":0,"name":"大威天龙100441","status":true,"sortOrder":null,"createTime":1585740601000,"updateTime":1585740601000},{"id":100442,"parentId":0,"name":"大威天龙100442","status":true,"sortOrder":null,"createTime":1585740624000,"updateTime":1585740624000},{"id":100452,"parentId":0,"name":"大威天龙100452","status":true,"sortOrder":null,"createTime":1585819171000,"updateTime":1585819171000},{"id":100453,"parentId":0,"name":"大威天龙100453","status":true,"sortOrder":null,"createTime":1585819353000,"updateTime":1585819353000},{"id":100460,"parentId":0,"name":"大威天龙100460","status":true,"sortOrder":null,"createTime":1585833219000,"updateTime":1585833219000},{"id":100461,"parentId":0,"name":"大威天龙100461","status":true,"sortOrder":null,"createTime":1585833249000,"updateTime":1585833249000},{"id":100462,"parentId":0,"name":"大威天龙100462","status":true,"sortOrder":null,"createTime":1585833698000,"updateTime":1585833698000},{"id":100463,"parentId":0,"name":"大威天龙100463","status":true,"sortOrder":null,"createTime":1585833719000,"updateTime":1585833719000},{"id":100465,"parentId":0,"name":"大威天龙100465","status":true,"sortOrder":null,"createTime":1585833887000,"updateTime":1585833887000},{"id":100467,"parentId":0,"name":"大威天龙100467","status":true,"sortOrder":null,"createTime":1585841886000,"updateTime":1585841886000},{"id":100468,"parentId":0,"name":"大威天龙100468","status":true,"sortOrder":null,"createTime":1585841937000,"updateTime":1585841937000},{"id":100469,"parentId":0,"name":"大威天龙100469","status":true,"sortOrder":null,"createTime":1585841971000,"updateTime":1585841971000},{"id":100472,"parentId":0,"name":"大威天龙100472","status":true,"sortOrder":null,"createTime":1585910990000,"updateTime":1585910990000},{"id":100473,"parentId":0,"name":"大威天龙100473","status":true,"sortOrder":null,"createTime":1585911307000,"updateTime":1585911307000},{"id":100474,"parentId":0,"name":"大威天龙100474","status":true,"sortOrder":null,"createTime":1585911392000,"updateTime":1585911392000},{"id":100475,"parentId":0,"name":"大威天龙100475","status":true,"sortOrder":null,"createTime":1585911481000,"updateTime":1585911481000},{"id":100480,"parentId":0,"name":"大威天龙100480","status":true,"sortOrder":null,"createTime":1585924164000,"updateTime":1585924164000},{"id":100482,"parentId":0,"name":"大威天龙100482","status":true,"sortOrder":null,"createTime":1585930539000,"updateTime":1585930539000},{"id":100486,"parentId":0,"name":"大威天龙100486","status":true,"sortOrder":null,"createTime":1586048490000,"updateTime":1586048490000},{"id":100489,"parentId":0,"name":"大威天龙100489","status":true,"sortOrder":null,"createTime":1586057297000,"updateTime":1586057297000},{"id":100490,"parentId":0,"name":"大威天龙100490","status":true,"sortOrder":null,"createTime":1586057332000,"updateTime":1586057332000},{"id":100494,"parentId":0,"name":"大威天龙100494","status":true,"sortOrder":null,"createTime":1586070914000,"updateTime":1586070914000},{"id":100499,"parentId":0,"name":"大威天龙100499","status":true,"sortOrder":null,"createTime":1586090060000,"updateTime":1586090060000},{"id":100500,"parentId":0,"name":"大威天龙100500","status":true,"sortOrder":null,"createTime":1586158563000,"updateTime":1586158563000},{"id":100502,"parentId":0,"name":"大威天龙100502","status":true,"sortOrder":null,"createTime":1586167137000,"updateTime":1586167137000},{"id":100504,"parentId":0,"name":"大威天龙100504","status":true,"sortOrder":null,"createTime":1586276584000,"updateTime":1586276584000},{"id":100506,"parentId":0,"name":"大威天龙100506","status":true,"sortOrder":null,"createTime":1586359553000,"updateTime":1586359553000},{"id":100508,"parentId":0,"name":"大威天龙100508","status":true,"sortOrder":null,"createTime":1586403303000,"updateTime":1586403303000},{"id":100509,"parentId":0,"name":"大威天龙100509","status":true,"sortOrder":null,"createTime":1586424718000,"updateTime":1586424718000},{"id":100510,"parentId":0,"name":"大威天龙100510","status":true,"sortOrder":null,"createTime":1586436288000,"updateTime":1586436288000},{"id":100511,"parentId":0,"name":"大威天龙100511","status":true,"sortOrder":null,"createTime":1586494976000,"updateTime":1586494976000},{"id":100513,"parentId":0,"name":"大威天龙100513","status":true,"sortOrder":null,"createTime":1586520293000,"updateTime":1586520293000},{"id":100514,"parentId":0,"name":"大威天龙100514","status":true,"sortOrder":null,"createTime":1586578768000,"updateTime":1586578768000},{"id":100515,"parentId":0,"name":"大威天龙100515","status":true,"sortOrder":null,"createTime":1586600141000,"updateTime":1586600141000},{"id":100516,"parentId":0,"name":"大威天龙100516","status":true,"sortOrder":null,"createTime":1586606051000,"updateTime":1586606051000},{"id":100519,"parentId":0,"name":"大威天龙100519","status":true,"sortOrder":null,"createTime":1586762854000,"updateTime":1586762854000},{"id":100520,"parentId":0,"name":"大威天龙100520","status":true,"sortOrder":null,"createTime":1586777664000,"updateTime":1586777664000},{"id":100524,"parentId":0,"name":"大威天龙100524","status":true,"sortOrder":null,"createTime":1586813916000,"updateTime":1586813916000},{"id":100529,"parentId":0,"name":"大威天龙100529","status":true,"sortOrder":null,"createTime":1586917047000,"updateTime":1586917047000},{"id":100530,"parentId":0,"name":"大威天龙100530","status":true,"sortOrder":null,"createTime":1586917082000,"updateTime":1586917082000},{"id":100533,"parentId":0,"name":"大威天龙100533","status":true,"sortOrder":null,"createTime":1586938440000,"updateTime":1586938440000},{"id":100534,"parentId":0,"name":"大威天龙100534","status":true,"sortOrder":null,"createTime":1586961440000,"updateTime":1586961440000},{"id":100536,"parentId":0,"name":"大威天龙100536","status":true,"sortOrder":null,"createTime":1587024298000,"updateTime":1587024298000},{"id":100538,"parentId":0,"name":"大威天龙100538","status":true,"sortOrder":null,"createTime":1587083886000,"updateTime":1587083886000},{"id":100542,"parentId":0,"name":"大威天龙100542","status":true,"sortOrder":null,"createTime":1587166274000,"updateTime":1587166274000},{"id":100543,"parentId":0,"name":"大威天龙100543","status":true,"sortOrder":null,"createTime":1587192998000,"updateTime":1587192998000},{"id":100544,"parentId":0,"name":"大威天龙100544","status":true,"sortOrder":null,"createTime":1587193618000,"updateTime":1587193618000},{"id":100545,"parentId":0,"name":"大威天龙100545","status":true,"sortOrder":null,"createTime":1587193637000,"updateTime":1587193637000},{"id":100551,"parentId":0,"name":"大威天龙100551","status":true,"sortOrder":null,"createTime":1587288885000,"updateTime":1587288885000},{"id":100552,"parentId":0,"name":"大威天龙100552","status":true,"sortOrder":null,"createTime":1587296543000,"updateTime":1587296543000},{"id":100555,"parentId":0,"name":"大威天龙100555","status":true,"sortOrder":null,"createTime":1587306714000,"updateTime":1587306714000},{"id":100558,"parentId":0,"name":"大威天龙100558","status":true,"sortOrder":null,"createTime":1587400900000,"updateTime":1587400900000},{"id":100561,"parentId":0,"name":"大威天龙100561","status":true,"sortOrder":null,"createTime":1587460515000,"updateTime":1587460515000},{"id":100562,"parentId":0,"name":"大威天龙100562","status":true,"sortOrder":null,"createTime":1587488216000,"updateTime":1587488216000},{"id":100565,"parentId":0,"name":"大威天龙100565","status":true,"sortOrder":null,"createTime":1587537395000,"updateTime":1587537395000},{"id":100574,"parentId":0,"name":"大威天龙100574","status":true,"sortOrder":null,"createTime":1587786549000,"updateTime":1587786549000},{"id":100575,"parentId":0,"name":"大威天龙100575","status":true,"sortOrder":null,"createTime":1587798696000,"updateTime":1587798696000},{"id":100576,"parentId":0,"name":"大威天龙100576","status":true,"sortOrder":null,"createTime":1587867532000,"updateTime":1587867532000},{"id":100577,"parentId":0,"name":"大威天龙100577","status":true,"sortOrder":null,"createTime":1587880414000,"updateTime":1587880414000},{"id":100578,"parentId":0,"name":"大威天龙100578","status":true,"sortOrder":null,"createTime":1587880422000,"updateTime":1587880422000},{"id":100580,"parentId":0,"name":"大威天龙100580","status":true,"sortOrder":null,"createTime":1588058475000,"updateTime":1588058475000},{"id":100581,"parentId":0,"name":"大威天龙100581","status":true,"sortOrder":null,"createTime":1588058486000,"updateTime":1588058486000},{"id":100583,"parentId":0,"name":"大威天龙100583","status":true,"sortOrder":null,"createTime":1588321335000,"updateTime":1588321335000},{"id":100587,"parentId":0,"name":"大威天龙100587","status":true,"sortOrder":null,"createTime":1588435909000,"updateTime":1588435909000},{"id":100589,"parentId":0,"name":"大威天龙100589","status":true,"sortOrder":null,"createTime":1588484342000,"updateTime":1588484342000},{"id":100590,"parentId":0,"name":"大威天龙100590","status":true,"sortOrder":null,"createTime":1588565836000,"updateTime":1588565836000},{"id":100596,"parentId":0,"name":"大威天龙100596","status":true,"sortOrder":null,"createTime":1588692744000,"updateTime":1588692744000},{"id":100601,"parentId":0,"name":"大威天龙100601","status":true,"sortOrder":null,"createTime":1588753376000,"updateTime":1588753376000},{"id":100602,"parentId":0,"name":"大威天龙100602","status":true,"sortOrder":null,"createTime":1588828300000,"updateTime":1588828300000},{"id":100604,"parentId":0,"name":"大威天龙100604","status":true,"sortOrder":null,"createTime":1588905388000,"updateTime":1588905388000},{"id":100605,"parentId":0,"name":"大威天龙100605","status":true,"sortOrder":null,"createTime":1588908341000,"updateTime":1588908341000},{"id":100608,"parentId":0,"name":"大威天龙100608","status":true,"sortOrder":null,"createTime":1588920177000,"updateTime":1588920177000},{"id":100609,"parentId":0,"name":"大威天龙100609","status":true,"sortOrder":null,"createTime":1588920261000,"updateTime":1588920261000},{"id":100610,"parentId":0,"name":"大威天龙100610","status":true,"sortOrder":null,"createTime":1588920288000,"updateTime":1588920288000},{"id":100611,"parentId":0,"name":"大威天龙100611","status":true,"sortOrder":null,"createTime":1588920328000,"updateTime":1588920328000},{"id":100612,"parentId":0,"name":"大威天龙100612","status":true,"sortOrder":null,"createTime":1588920476000,"updateTime":1588920476000},{"id":100614,"parentId":0,"name":"大威天龙100614","status":true,"sortOrder":null,"createTime":1588928614000,"updateTime":1588928614000},{"id":100615,"parentId":0,"name":"大威天龙100615","status":true,"sortOrder":null,"createTime":1588980376000,"updateTime":1588980376000},{"id":100618,"parentId":0,"name":"大威天龙100618","status":true,"sortOrder":null,"createTime":1588997125000,"updateTime":1588997125000},{"id":100625,"parentId":0,"name":"大威天龙100625","status":true,"sortOrder":null,"createTime":1589112241000,"updateTime":1589112241000},{"id":100626,"parentId":0,"name":"大威天龙100626","status":true,"sortOrder":null,"createTime":1589163563000,"updateTime":1589163563000},{"id":100627,"parentId":0,"name":"大威天龙100627","status":true,"sortOrder":null,"createTime":1589163610000,"updateTime":1589163610000},{"id":100628,"parentId":0,"name":"大威天龙100628","status":true,"sortOrder":null,"createTime":1589163757000,"updateTime":1589163757000},{"id":100629,"parentId":0,"name":"大威天龙100629","status":true,"sortOrder":null,"createTime":1589164303000,"updateTime":1589164303000},{"id":100633,"parentId":0,"name":"大威天龙100633","status":true,"sortOrder":null,"createTime":1589182685000,"updateTime":1589182685000},{"id":100634,"parentId":0,"name":"大威天龙100634","status":true,"sortOrder":null,"createTime":1589183216000,"updateTime":1589183216000},{"id":100637,"parentId":0,"name":"大威天龙100637","status":true,"sortOrder":null,"createTime":1589206914000,"updateTime":1589206914000},{"id":100638,"parentId":0,"name":"大威天龙100638","status":true,"sortOrder":null,"createTime":1589206930000,"updateTime":1589206930000},{"id":100639,"parentId":0,"name":"大威天龙100639","status":true,"sortOrder":null,"createTime":1589248454000,"updateTime":1589248454000},{"id":100640,"parentId":0,"name":"大威天龙100640","status":true,"sortOrder":null,"createTime":1589248564000,"updateTime":1589248564000},{"id":100641,"parentId":0,"name":"大威天龙100641","status":true,"sortOrder":null,"createTime":1589252295000,"updateTime":1589252295000},{"id":100643,"parentId":0,"name":"大威天龙100643","status":true,"sortOrder":null,"createTime":1589253346000,"updateTime":1589253346000},{"id":100647,"parentId":0,"name":"大威天龙100647","status":true,"sortOrder":null,"createTime":1589267909000,"updateTime":1589267909000},{"id":100649,"parentId":0,"name":"大威天龙100649","status":true,"sortOrder":null,"createTime":1589340320000,"updateTime":1589340320000},{"id":100651,"parentId":0,"name":"大威天龙100651","status":true,"sortOrder":null,"createTime":1589341211000,"updateTime":1589341211000},{"id":100652,"parentId":0,"name":"大威天龙100652","status":true,"sortOrder":null,"createTime":1589345420000,"updateTime":1589345420000},{"id":100655,"parentId":0,"name":"大威天龙100655","status":true,"sortOrder":null,"createTime":1589352219000,"updateTime":1589352219000},{"id":100656,"parentId":0,"name":"大威天龙100656","status":true,"sortOrder":null,"createTime":1589353411000,"updateTime":1589353411000},{"id":100657,"parentId":0,"name":"大威天龙100657","status":true,"sortOrder":null,"createTime":1589353632000,"updateTime":1589353632000},{"id":100658,"parentId":0,"name":"大威天龙100658","status":true,"sortOrder":null,"createTime":1589354793000,"updateTime":1589354793000},{"id":100660,"parentId":0,"name":"大威天龙100660","status":true,"sortOrder":null,"createTime":1589355845000,"updateTime":1589355845000},{"id":100664,"parentId":0,"name":"大威天龙100664","status":true,"sortOrder":null,"createTime":1589361931000,"updateTime":1589361931000},{"id":100665,"parentId":0,"name":"大威天龙100665","status":true,"sortOrder":null,"createTime":1589373790000,"updateTime":1589373790000},{"id":100666,"parentId":0,"name":"大威天龙100666","status":true,"sortOrder":null,"createTime":1589375201000,"updateTime":1589375201000},{"id":100667,"parentId":0,"name":"大威天龙100667","status":true,"sortOrder":null,"createTime":1589376840000,"updateTime":1589376840000},{"id":100669,"parentId":0,"name":"大威天龙100669","status":true,"sortOrder":null,"createTime":1589381755000,"updateTime":1589381755000},{"id":100671,"parentId":0,"name":"大威天龙100671","status":true,"sortOrder":null,"createTime":1589388199000,"updateTime":1589388199000},{"id":100672,"parentId":0,"name":"大威天龙100672","status":true,"sortOrder":null,"createTime":1589396973000,"updateTime":1589396973000},{"id":100675,"parentId":0,"name":"大威天龙100675","status":true,"sortOrder":null,"createTime":1589431742000,"updateTime":1589431742000},{"id":100676,"parentId":0,"name":"大威天龙100676","status":true,"sortOrder":null,"createTime":1589432143000,"updateTime":1589432143000},{"id":100677,"parentId":0,"name":"大威天龙100677","status":true,"sortOrder":null,"createTime":1589432157000,"updateTime":1589432157000},{"id":100678,"parentId":0,"name":"大威天龙100678","status":true,"sortOrder":null,"createTime":1589432166000,"updateTime":1589432166000},{"id":100679,"parentId":0,"name":"大威天龙100679","status":true,"sortOrder":null,"createTime":1589432177000,"updateTime":1589432177000},{"id":100680,"parentId":0,"name":"大威天龙100680","status":true,"sortOrder":null,"createTime":1589432391000,"updateTime":1589432391000},{"id":100681,"parentId":0,"name":"大威天龙100681","status":true,"sortOrder":null,"createTime":1589432407000,"updateTime":1589432407000},{"id":100682,"parentId":0,"name":"大威天龙100682","status":true,"sortOrder":null,"createTime":1589432429000,"updateTime":1589432429000},{"id":100683,"parentId":0,"name":"大威天龙100683","status":true,"sortOrder":null,"createTime":1589432455000,"updateTime":1589432455000},{"id":100684,"parentId":0,"name":"大威天龙100684","status":true,"sortOrder":null,"createTime":1589432500000,"updateTime":1589432500000},{"id":100685,"parentId":0,"name":"大威天龙100685","status":true,"sortOrder":null,"createTime":1589432552000,"updateTime":1589432552000},{"id":100686,"parentId":0,"name":"大威天龙100686","status":true,"sortOrder":null,"createTime":1589433244000,"updateTime":1589433244000},{"id":100687,"parentId":0,"name":"大威天龙100687","status":true,"sortOrder":null,"createTime":1589433561000,"updateTime":1589433561000},{"id":100688,"parentId":0,"name":"大威天龙100688","status":true,"sortOrder":null,"createTime":1589433627000,"updateTime":1589433627000},{"id":100692,"parentId":0,"name":"大威天龙100692","status":true,"sortOrder":null,"createTime":1589437516000,"updateTime":1589437516000},{"id":100693,"parentId":0,"name":"大威天龙100693","status":true,"sortOrder":null,"createTime":1589437701000,"updateTime":1589437701000},{"id":100697,"parentId":0,"name":"大威天龙100697","status":true,"sortOrder":null,"createTime":1589441940000,"updateTime":1589441940000},{"id":100698,"parentId":0,"name":"大威天龙100698","status":true,"sortOrder":null,"createTime":1589443128000,"updateTime":1589443128000},{"id":100699,"parentId":0,"name":"大威天龙100699","status":true,"sortOrder":null,"createTime":1589443181000,"updateTime":1589443181000},{"id":100700,"parentId":0,"name":"大威天龙100700","status":true,"sortOrder":null,"createTime":1589444034000,"updateTime":1589444034000},{"id":100702,"parentId":0,"name":"大威天龙100702","status":true,"sortOrder":null,"createTime":1589447702000,"updateTime":1589447702000},{"id":100704,"parentId":0,"name":"大威天龙100704","status":true,"sortOrder":null,"createTime":1589453549000,"updateTime":1589453549000},{"id":100705,"parentId":0,"name":"大威天龙100705","status":true,"sortOrder":null,"createTime":1589454743000,"updateTime":1589454743000},{"id":100707,"parentId":0,"name":"大威天龙100707","status":true,"sortOrder":null,"createTime":1589455042000,"updateTime":1589455042000},{"id":100708,"parentId":0,"name":"大威天龙100708","status":true,"sortOrder":null,"createTime":1589455132000,"updateTime":1589455132000},{"id":100709,"parentId":0,"name":"大威天龙100709","status":true,"sortOrder":null,"createTime":1589455614000,"updateTime":1589455614000},{"id":100710,"parentId":0,"name":"大威天龙100710","status":true,"sortOrder":null,"createTime":1589455964000,"updateTime":1589455964000},{"id":100712,"parentId":0,"name":"大威天龙100712","status":true,"sortOrder":null,"createTime":1589456488000,"updateTime":1589456488000},{"id":100713,"parentId":0,"name":"大威天龙100713","status":true,"sortOrder":null,"createTime":1589456572000,"updateTime":1589456572000},{"id":100714,"parentId":0,"name":"大威天龙100714","status":true,"sortOrder":null,"createTime":1589456669000,"updateTime":1589456669000},{"id":100716,"parentId":0,"name":"大威天龙100716","status":true,"sortOrder":null,"createTime":1589462166000,"updateTime":1589462166000},{"id":100720,"parentId":0,"name":"大威天龙100720","status":true,"sortOrder":null,"createTime":1589471998000,"updateTime":1589471998000},{"id":100721,"parentId":0,"name":"大威天龙100721","status":true,"sortOrder":null,"createTime":1589473950000,"updateTime":1589473950000},{"id":100722,"parentId":0,"name":"大威天龙100722","status":true,"sortOrder":null,"createTime":1589474174000,"updateTime":1589474174000},{"id":100723,"parentId":0,"name":"大威天龙100723","status":true,"sortOrder":null,"createTime":1589477056000,"updateTime":1589477056000},{"id":100724,"parentId":0,"name":"大威天龙100724","status":true,"sortOrder":null,"createTime":1589477179000,"updateTime":1589477179000},{"id":100725,"parentId":0,"name":"大威天龙100725","status":true,"sortOrder":null,"createTime":1589480485000,"updateTime":1589480485000},{"id":100726,"parentId":0,"name":"大威天龙100726","status":true,"sortOrder":null,"createTime":1589480530000,"updateTime":1589480530000},{"id":100727,"parentId":0,"name":"大威天龙100727","status":true,"sortOrder":null,"createTime":1589480561000,"updateTime":1589480561000},{"id":100732,"parentId":0,"name":"大威天龙100732","status":true,"sortOrder":null,"createTime":1589535121000,"updateTime":1589535121000},{"id":100733,"parentId":0,"name":"大威天龙100733","status":true,"sortOrder":null,"createTime":1589536198000,"updateTime":1589536198000},{"id":100734,"parentId":0,"name":"大威天龙100734","status":true,"sortOrder":null,"createTime":1589536200000,"updateTime":1589536200000},{"id":100735,"parentId":0,"name":"大威天龙100735","status":true,"sortOrder":null,"createTime":1589602532000,"updateTime":1589602532000},{"id":100737,"parentId":0,"name":"大威天龙100737","status":true,"sortOrder":null,"createTime":1589618325000,"updateTime":1589618325000},{"id":100738,"parentId":0,"name":"大威天龙100738","status":true,"sortOrder":null,"createTime":1589618326000,"updateTime":1589618326000},{"id":100739,"parentId":0,"name":"大威天龙100739","status":true,"sortOrder":null,"createTime":1589618326000,"updateTime":1589618326000},{"id":100740,"parentId":0,"name":"大威天龙100740","status":true,"sortOrder":null,"createTime":1589618326000,"updateTime":1589618326000},{"id":100741,"parentId":0,"name":"大威天龙100741","status":true,"sortOrder":null,"createTime":1589648160000,"updateTime":1589648160000},{"id":100742,"parentId":0,"name":"大威天龙100742","status":true,"sortOrder":null,"createTime":1589770657000,"updateTime":1589770657000},{"id":100743,"parentId":0,"name":"大威天龙100743","status":true,"sortOrder":null,"createTime":1589784143000,"updateTime":1589784143000},{"id":100744,"parentId":0,"name":"大威天龙100744","status":true,"sortOrder":null,"createTime":1589788871000,"updateTime":1589788871000},{"id":100748,"parentId":0,"name":"大威天龙100748","status":true,"sortOrder":null,"createTime":1589850888000,"updateTime":1589850888000},{"id":100753,"parentId":0,"name":"大威天龙100753","status":true,"sortOrder":null,"createTime":1590049986000,"updateTime":1590049986000},{"id":100760,"parentId":0,"name":"大威天龙100760","status":true,"sortOrder":null,"createTime":1590096940000,"updateTime":1590096940000},{"id":100761,"parentId":0,"name":"大威天龙100761","status":true,"sortOrder":null,"createTime":1590096959000,"updateTime":1590096959000},{"id":100762,"parentId":0,"name":"大威天龙100762","status":true,"sortOrder":null,"createTime":1590096984000,"updateTime":1590096984000},{"id":100763,"parentId":0,"name":"大威天龙100763","status":true,"sortOrder":null,"createTime":1590096996000,"updateTime":1590096996000},{"id":100764,"parentId":0,"name":"大威天龙100764","status":true,"sortOrder":null,"createTime":1590097005000,"updateTime":1590097005000},{"id":100765,"parentId":0,"name":"大威天龙100765","status":true,"sortOrder":null,"createTime":1590097024000,"updateTime":1590097024000},{"id":100766,"parentId":0,"name":"大威天龙100766","status":true,"sortOrder":null,"createTime":1590097118000,"updateTime":1590097118000},{"id":100767,"parentId":0,"name":"大威天龙100767","status":true,"sortOrder":null,"createTime":1590097129000,"updateTime":1590097129000},{"id":100768,"parentId":0,"name":"大威天龙100768","status":true,"sortOrder":null,"createTime":1590097151000,"updateTime":1590097151000},{"id":100769,"parentId":0,"name":"大威天龙100769","status":true,"sortOrder":null,"createTime":1590097161000,"updateTime":1590097161000},{"id":100770,"parentId":0,"name":"大威天龙100770","status":true,"sortOrder":null,"createTime":1590097179000,"updateTime":1590097179000},{"id":100771,"parentId":0,"name":"大威天龙100771","status":true,"sortOrder":null,"createTime":1590097189000,"updateTime":1590097189000},{"id":100772,"parentId":0,"name":"大威天龙100772","status":true,"sortOrder":null,"createTime":1590097203000,"updateTime":1590097203000},{"id":100773,"parentId":0,"name":"大威天龙100773","status":true,"sortOrder":null,"createTime":1590097226000,"updateTime":1590097226000},{"id":100774,"parentId":0,"name":"大威天龙100774","status":true,"sortOrder":null,"createTime":1590097243000,"updateTime":1590097243000},{"id":100775,"parentId":0,"name":"大威天龙100775","status":true,"sortOrder":null,"createTime":1590097252000,"updateTime":1590097252000},{"id":100776,"parentId":0,"name":"大威天龙100776","status":true,"sortOrder":null,"createTime":1590097267000,"updateTime":1590097267000},{"id":100777,"parentId":0,"name":"大威天龙100777","status":true,"sortOrder":null,"createTime":1590097280000,"updateTime":1590097280000},{"id":100778,"parentId":0,"name":"大威天龙100778","status":true,"sortOrder":null,"createTime":1590097332000,"updateTime":1590097332000},{"id":100779,"parentId":0,"name":"大威天龙100779","status":true,"sortOrder":null,"createTime":1590097348000,"updateTime":1590097348000},{"id":100780,"parentId":0,"name":"大威天龙100780","status":true,"sortOrder":null,"createTime":1590115776000,"updateTime":1590115776000},{"id":100784,"parentId":0,"name":"大威天龙100784","status":true,"sortOrder":null,"createTime":1590331559000,"updateTime":1590331559000},{"id":100787,"parentId":0,"name":"大威天龙100787","status":true,"sortOrder":null,"createTime":1590369347000,"updateTime":1590369347000},{"id":100788,"parentId":0,"name":"大威天龙100788","status":true,"sortOrder":null,"createTime":1590420346000,"updateTime":1590420346000},{"id":100790,"parentId":0,"name":"大威天龙100790","status":true,"sortOrder":null,"createTime":1590478698000,"updateTime":1590478698000},{"id":100791,"parentId":0,"name":"大威天龙100791","status":true,"sortOrder":null,"createTime":1590478713000,"updateTime":1590478713000},{"id":100795,"parentId":0,"name":"大威天龙100795","status":true,"sortOrder":null,"createTime":1590485793000,"updateTime":1590485793000},{"id":100796,"parentId":0,"name":"大威天龙100796","status":true,"sortOrder":null,"createTime":1590485990000,"updateTime":1590485990000},{"id":100797,"parentId":0,"name":"大威天龙100797","status":true,"sortOrder":null,"createTime":1590486407000,"updateTime":1590486407000},{"id":100798,"parentId":0,"name":"大威天龙100798","status":true,"sortOrder":null,"createTime":1590486420000,"updateTime":1590486420000},{"id":100799,"parentId":0,"name":"大威天龙100799","status":true,"sortOrder":null,"createTime":1590486488000,"updateTime":1590486488000},{"id":100800,"parentId":0,"name":"大威天龙100800","status":true,"sortOrder":null,"createTime":1590486684000,"updateTime":1590486684000},{"id":100806,"parentId":0,"name":"大威天龙100806","status":true,"sortOrder":null,"createTime":1590561730000,"updateTime":1590561730000},{"id":100808,"parentId":0,"name":"大威天龙100808","status":true,"sortOrder":null,"createTime":1590568160000,"updateTime":1590568160000},{"id":100809,"parentId":0,"name":"大威天龙100809","status":true,"sortOrder":null,"createTime":1590569490000,"updateTime":1590569490000},{"id":100811,"parentId":0,"name":"大威天龙100811","status":true,"sortOrder":null,"createTime":1590635181000,"updateTime":1590635181000},{"id":100814,"parentId":0,"name":"大威天龙100814","status":true,"sortOrder":null,"createTime":1590715024000,"updateTime":1590715024000},{"id":100817,"parentId":0,"name":"大威天龙100817","status":true,"sortOrder":null,"createTime":1590722295000,"updateTime":1590722295000},{"id":100820,"parentId":0,"name":"大威天龙100820","status":true,"sortOrder":null,"createTime":1590722474000,"updateTime":1590722474000},{"id":100821,"parentId":0,"name":"大威天龙100821","status":true,"sortOrder":null,"createTime":1590722478000,"updateTime":1590722478000},{"id":100822,"parentId":0,"name":"大威天龙100822","status":true,"sortOrder":null,"createTime":1590722482000,"updateTime":1590722482000},{"id":100823,"parentId":0,"name":"大威天龙100823","status":true,"sortOrder":null,"createTime":1590722507000,"updateTime":1590722507000},{"id":100824,"parentId":0,"name":"大威天龙100824","status":true,"sortOrder":null,"createTime":1590722516000,"updateTime":1590722516000},{"id":100825,"parentId":0,"name":"大威天龙100825","status":true,"sortOrder":null,"createTime":1590723474000,"updateTime":1590723474000},{"id":100826,"parentId":0,"name":"大威天龙100826","status":true,"sortOrder":null,"createTime":1590723651000,"updateTime":1590723651000},{"id":100827,"parentId":0,"name":"大威天龙100827","status":true,"sortOrder":null,"createTime":1590733564000,"updateTime":1590733564000},{"id":100829,"parentId":0,"name":"大威天龙100829","status":true,"sortOrder":null,"createTime":1590756526000,"updateTime":1590756526000},{"id":100831,"parentId":0,"name":"大威天龙100831","status":true,"sortOrder":null,"createTime":1590763019000,"updateTime":1590763019000},{"id":100834,"parentId":0,"name":"大威天龙100834","status":true,"sortOrder":null,"createTime":1590907243000,"updateTime":1590907243000},{"id":100835,"parentId":0,"name":"大威天龙100835","status":true,"sortOrder":null,"createTime":1590907255000,"updateTime":1590907255000},{"id":100836,"parentId":0,"name":"大威天龙100836","status":true,"sortOrder":null,"createTime":1590911752000,"updateTime":1590911752000},{"id":100839,"parentId":0,"name":"大威天龙100839","status":true,"sortOrder":null,"createTime":1590912479000,"updateTime":1590912479000},{"id":100840,"parentId":0,"name":"大威天龙100840","status":true,"sortOrder":null,"createTime":1590913967000,"updateTime":1590913967000},{"id":100841,"parentId":0,"name":"大威天龙100841","status":true,"sortOrder":null,"createTime":1590914000000,"updateTime":1590914000000},{"id":100843,"parentId":0,"name":"大威天龙100843","status":true,"sortOrder":null,"createTime":1590931062000,"updateTime":1590931062000},{"id":100844,"parentId":0,"name":"大威天龙100844","status":true,"sortOrder":null,"createTime":1590931097000,"updateTime":1590931097000},{"id":100845,"parentId":0,"name":"大威天龙100845","status":true,"sortOrder":null,"createTime":1590931457000,"updateTime":1590931457000},{"id":100847,"parentId":0,"name":"大威天龙100847","status":true,"sortOrder":null,"createTime":1590931725000,"updateTime":1590931725000},{"id":100848,"parentId":0,"name":"大威天龙100848","status":true,"sortOrder":null,"createTime":1590935593000,"updateTime":1590935593000},{"id":100849,"parentId":0,"name":"大威天龙100849","status":true,"sortOrder":null,"createTime":1590940148000,"updateTime":1590940148000},{"id":100853,"parentId":0,"name":"大威天龙100853","status":true,"sortOrder":null,"createTime":1590992193000,"updateTime":1590992193000},{"id":100854,"parentId":0,"name":"大威天龙100854","status":true,"sortOrder":null,"createTime":1590992213000,"updateTime":1590992213000},{"id":100855,"parentId":0,"name":"大威天龙100855","status":true,"sortOrder":null,"createTime":1590992398000,"updateTime":1590992398000},{"id":100859,"parentId":0,"name":"大威天龙100859","status":true,"sortOrder":null,"createTime":1591017338000,"updateTime":1591017338000},{"id":100861,"parentId":0,"name":"大威天龙100861","status":true,"sortOrder":null,"createTime":1591019687000,"updateTime":1591019687000},{"id":100865,"parentId":0,"name":"大威天龙100865","status":true,"sortOrder":null,"createTime":1591022151000,"updateTime":1591022151000},{"id":100866,"parentId":0,"name":"大威天龙100866","status":true,"sortOrder":null,"createTime":1591022288000,"updateTime":1591022288000},{"id":100867,"parentId":0,"name":"大威天龙100867","status":true,"sortOrder":null,"createTime":1591022316000,"updateTime":1591022316000},{"id":100868,"parentId":0,"name":"大威天龙100868","status":true,"sortOrder":null,"createTime":1591022497000,"updateTime":1591022497000},{"id":100869,"parentId":0,"name":"大威天龙100869","status":true,"sortOrder":null,"createTime":1591023394000,"updateTime":1591023394000},{"id":100870,"parentId":0,"name":"大威天龙100870","status":true,"sortOrder":null,"createTime":1591024212000,"updateTime":1591024212000},{"id":100871,"parentId":0,"name":"大威天龙100871","status":true,"sortOrder":null,"createTime":1591024426000,"updateTime":1591024426000},{"id":100872,"parentId":0,"name":"大威天龙100872","status":true,"sortOrder":null,"createTime":1591025180000,"updateTime":1591025180000},{"id":100873,"parentId":0,"name":"大威天龙100873","status":true,"sortOrder":null,"createTime":1591026135000,"updateTime":1591026135000},{"id":100874,"parentId":0,"name":"大威天龙100874","status":true,"sortOrder":null,"createTime":1591026423000,"updateTime":1591026423000},{"id":100875,"parentId":0,"name":"大威天龙100875","status":true,"sortOrder":null,"createTime":1591103639000,"updateTime":1591103639000},{"id":100879,"parentId":0,"name":"大威天龙100879","status":true,"sortOrder":null,"createTime":1591346366000,"updateTime":1591346366000},{"id":100880,"parentId":0,"name":"大威天龙100880","status":true,"sortOrder":null,"createTime":1591346404000,"updateTime":1591346404000},{"id":100881,"parentId":0,"name":"大威天龙100881","status":true,"sortOrder":null,"createTime":1591355369000,"updateTime":1591355369000},{"id":100887,"parentId":0,"name":"大威天龙100887","status":true,"sortOrder":null,"createTime":1591648929000,"updateTime":1591648929000},{"id":100889,"parentId":0,"name":"大威天龙100889","status":true,"sortOrder":null,"createTime":1591671761000,"updateTime":1591671761000},{"id":100891,"parentId":0,"name":"大威天龙100891","status":true,"sortOrder":null,"createTime":1591691447000,"updateTime":1591691447000},{"id":100897,"parentId":0,"name":"大威天龙100897","status":true,"sortOrder":null,"createTime":1592133557000,"updateTime":1592133557000},{"id":100903,"parentId":0,"name":"lidonhon","status":true,"sortOrder":null,"createTime":1592749584000,"updateTime":1592749584000},{"id":100904,"parentId":0,"name":"155","status":true,"sortOrder":null,"createTime":1592749622000,"updateTime":1592749622000},{"id":100905,"parentId":0,"name":"sssssssssss","status":true,"sortOrder":null,"createTime":1592802334000,"updateTime":1592802334000},{"id":100907,"parentId":0,"name":"955","status":true,"sortOrder":null,"createTime":1592803078000,"updateTime":1592803078000},{"id":100909,"parentId":0,"name":"李东的项目","status":true,"sortOrder":null,"createTime":1592843007000,"updateTime":1592843007000},{"id":100910,"parentId":0,"name":"45","status":true,"sortOrder":null,"createTime":1592978038000,"updateTime":1592978038000},{"id":100911,"parentId":0,"name":"一级品类测试00000011111","status":true,"sortOrder":null,"createTime":1593096131000,"updateTime":1593096131000},{"id":100913,"parentId":0,"name":"水果","status":true,"sortOrder":null,"createTime":1593415596000,"updateTime":1593415596000},{"id":100916,"parentId":0,"name":"nih","status":true,"sortOrder":null,"createTime":1593739074000,"updateTime":1593739074000},{"id":100919,"parentId":0,"name":"一级吧","status":true,"sortOrder":null,"createTime":1593758343000,"updateTime":1593758343000},{"id":100925,"parentId":0,"name":"lll","status":true,"sortOrder":null,"createTime":1594721305000,"updateTime":1594721305000},{"id":100929,"parentId":0,"name":"First category","status":true,"sortOrder":null,"createTime":1595142282000,"updateTime":1595142282000},{"id":100930,"parentId":0,"name":"111122","status":true,"sortOrder":null,"createTime":1595142851000,"updateTime":1595142851000},{"id":100933,"parentId":0,"name":"山姆大叔的測試節點","status":true,"sortOrder":null,"createTime":1595230519000,"updateTime":1595230519000},{"id":100935,"parentId":0,"name":"a's'da's'd","status":true,"sortOrder":null,"createTime":1595253825000,"updateTime":1595253825000},{"id":100937,"parentId":0,"name":"23","status":true,"sortOrder":null,"createTime":1595421985000,"updateTime":1595421985000},{"id":100938,"parentId":0,"name":"wahaha","status":true,"sortOrder":null,"createTime":1595428647000,"updateTime":1595428647000},{"id":100941,"parentId":0,"name":"wyrTest-1","status":true,"sortOrder":null,"createTime":1595485951000,"updateTime":1595485951000},{"id":100945,"parentId":0,"name":"崩坏三","status":true,"sortOrder":null,"createTime":1595647080000,"updateTime":1595647080000},{"id":100951,"parentId":0,"name":"20200728","status":true,"sortOrder":null,"createTime":1595947086000,"updateTime":1595947086000},{"id":100956,"parentId":0,"name":"nin","status":true,"sortOrder":null,"createTime":1595993376000,"updateTime":1595993376000},{"id":100958,"parentId":0,"name":"车","status":true,"sortOrder":null,"createTime":1596241589000,"updateTime":1596241589000},{"id":100960,"parentId":0,"name":"123","status":true,"sortOrder":null,"createTime":1596673973000,"updateTime":1596673973000},{"id":100965,"parentId":0,"name":"4444","status":true,"sortOrder":null,"createTime":1596724760000,"updateTime":1596724760000},{"id":100966,"parentId":0,"name":"抄抄炒","status":true,"sortOrder":null,"createTime":1596756398000,"updateTime":1596756398000},{"id":100968,"parentId":0,"name":"抄抄炒","status":true,"sortOrder":null,"createTime":1596774636000,"updateTime":1596774636000},{"id":100973,"parentId":0,"name":"d","status":true,"sortOrder":null,"createTime":1596802625000,"updateTime":1596802625000},{"id":100974,"parentId":0,"name":"吕思格","status":true,"sortOrder":null,"createTime":1596802672000,"updateTime":1596802672000},{"id":100975,"parentId":0,"name":"86786684","status":true,"sortOrder":null,"createTime":1596802838000,"updateTime":1596802838000},{"id":100977,"parentId":0,"name":"吕思格a'a'a","status":true,"sortOrder":null,"createTime":1596803366000,"updateTime":1596803366000},{"id":100978,"parentId":0,"name":"ddd","status":true,"sortOrder":null,"createTime":1596816305000,"updateTime":1596816305000},{"id":100979,"parentId":0,"name":"ddd","status":true,"sortOrder":null,"createTime":1596816375000,"updateTime":1596816375000},{"id":100980,"parentId":0,"name":"ddd","status":true,"sortOrder":null,"createTime":1596816596000,"updateTime":1596816596000},{"id":100981,"parentId":0,"name":"ddd","status":true,"sortOrder":null,"createTime":1596816636000,"updateTime":1596816636000},{"id":100982,"parentId":0,"name":"ddd","status":true,"sortOrder":null,"createTime":1596816759000,"updateTime":1596816759000},{"id":100983,"parentId":0,"name":"ddd","status":true,"sortOrder":null,"createTime":1596817459000,"updateTime":1596817459000},{"id":100984,"parentId":0,"name":"ddd","status":true,"sortOrder":null,"createTime":1596817564000,"updateTime":1596817564000},{"id":100985,"parentId":0,"name":"ddd","status":true,"sortOrder":null,"createTime":1596817568000,"updateTime":1596817568000},{"id":100986,"parentId":0,"name":"ddd","status":true,"sortOrder":null,"createTime":1596817599000,"updateTime":1596817599000},{"id":100987,"parentId":0,"name":"ddd","status":true,"sortOrder":null,"createTime":1596817603000,"updateTime":1596817603000},{"id":100988,"parentId":0,"name":"ddd","status":true,"sortOrder":null,"createTime":1596817616000,"updateTime":1596817616000},{"id":100989,"parentId":0,"name":"ddd","status":true,"sortOrder":null,"createTime":1596817700000,"updateTime":1596817700000},{"id":100990,"parentId":0,"name":"ddd","status":true,"sortOrder":null,"createTime":1596818397000,"updateTime":1596818397000},{"id":100991,"parentId":0,"name":"ddd","status":true,"sortOrder":null,"createTime":1596818559000,"updateTime":1596818559000},{"id":100992,"parentId":0,"name":"ddd","status":true,"sortOrder":null,"createTime":1596818601000,"updateTime":1596818601000},{"id":100993,"parentId":0,"name":"ddd","status":true,"sortOrder":null,"createTime":1596818622000,"updateTime":1596818622000},{"id":100994,"parentId":0,"name":"ddd","status":true,"sortOrder":null,"createTime":1596818636000,"updateTime":1596818636000},{"id":100996,"parentId":0,"name":"安慰输入的头发晕","status":true,"sortOrder":null,"createTime":1596818794000,"updateTime":1596818794000},{"id":100997,"parentId":0,"name":"阿师傅大哥","status":true,"sortOrder":null,"createTime":1596818909000,"updateTime":1596818909000},{"id":100998,"parentId":0,"name":"水电费","status":true,"sortOrder":null,"createTime":1596819425000,"updateTime":1596819425000},{"id":100999,"parentId":0,"name":"睡觉","status":true,"sortOrder":null,"createTime":1596819536000,"updateTime":1596819536000},{"id":101000,"parentId":0,"name":"嘻嘻一嘻嘻嘻嘻嘻嘻嘻  jiang ---hao","status":true,"sortOrder":null,"createTime":1596819711000,"updateTime":1596819711000},{"id":101001,"parentId":0,"name":"爱德华郭敬明","status":true,"sortOrder":null,"createTime":1596819740000,"updateTime":1596819740000},{"id":101002,"parentId":0,"name":"双方都","status":true,"sortOrder":null,"createTime":1596819782000,"updateTime":1596819782000},{"id":101003,"parentId":0,"name":"快点睡觉啦  小小jiang--hao","status":true,"sortOrder":null,"createTime":1596819840000,"updateTime":1596819840000},{"id":101004,"parentId":0,"name":"晚安安安","status":true,"sortOrder":null,"createTime":1596819901000,"updateTime":1596819901000},{"id":101005,"parentId":0,"name":"康帅","status":true,"sortOrder":null,"createTime":1596846799000,"updateTime":1596846799000},{"id":101006,"parentId":0,"name":"吕思格","status":true,"sortOrder":null,"createTime":1596847381000,"updateTime":1596847381000},{"id":101007,"parentId":0,"name":"吕思格222","status":true,"sortOrder":null,"createTime":1596847604000,"updateTime":1596847604000},{"id":101009,"parentId":0,"name":"嘿嘿","status":true,"sortOrder":null,"createTime":1596847618000,"updateTime":1596847618000},{"id":101010,"parentId":0,"name":"drtbk","status":true,"sortOrder":null,"createTime":1596847632000,"updateTime":1596847632000},{"id":101011,"parentId":0,"name":"我要给他人","status":true,"sortOrder":null,"createTime":1596847652000,"updateTime":1596847652000},{"id":101012,"parentId":0,"name":"废机油","status":true,"sortOrder":null,"createTime":1596847689000,"updateTime":1596847689000},{"id":101013,"parentId":0,"name":"凹凸曼","status":true,"sortOrder":null,"createTime":1596868067000,"updateTime":1596868067000},{"id":101017,"parentId":0,"name":"g","status":true,"sortOrder":null,"createTime":1596873010000,"updateTime":1596873010000},{"id":101018,"parentId":0,"name":"love","status":true,"sortOrder":null,"createTime":1596873607000,"updateTime":1596873607000},{"id":101021,"parentId":0,"name":"12","status":true,"sortOrder":null,"createTime":1596875760000,"updateTime":1596875760000},{"id":101024,"parentId":0,"name":"dsgfh","status":true,"sortOrder":null,"createTime":1596878902000,"updateTime":1596878902000},{"id":101027,"parentId":0,"name":"阿斯顿撒","status":true,"sortOrder":null,"createTime":1596884273000,"updateTime":1596884273000},{"id":101032,"parentId":0,"name":"vfdsbgfsbgf","status":true,"sortOrder":null,"createTime":1596952767000,"updateTime":1596952767000},{"id":101034,"parentId":0,"name":"三国bgm","status":true,"sortOrder":null,"createTime":1596955985000,"updateTime":1596955985000},{"id":101044,"parentId":0,"name":"321321","status":true,"sortOrder":null,"createTime":1597160507000,"updateTime":1597160507000},{"id":101045,"parentId":0,"name":"321321","status":true,"sortOrder":null,"createTime":1597160507000,"updateTime":1597160507000},{"id":101046,"parentId":0,"name":"321321","status":true,"sortOrder":null,"createTime":1597160508000,"updateTime":1597160508000},{"id":101047,"parentId":0,"name":"321321","status":true,"sortOrder":null,"createTime":1597160508000,"updateTime":1597160508000},{"id":101048,"parentId":0,"name":"321321","status":true,"sortOrder":null,"createTime":1597160508000,"updateTime":1597160508000},{"id":101051,"parentId":0,"name":"佛道","status":true,"sortOrder":null,"createTime":1597240792000,"updateTime":1597240792000}]}